iotiumlib/__init__.py
iotiumlib/cluster.py
iotiumlib/download.py
iotiumlib/firewall.py
iotiumlib/helper.py
iotiumlib/image.py
iotiumlib/network.py
iotiumlib/node.py
iotiumlib/nodecli.py
iotiumlib/orch.py
iotiumlib/orchlogin.py
iotiumlib/org.py
iotiumlib/pki.py
iotiumlib/profile.py
iotiumlib/secret.py
iotiumlib/service.py
iotiumlib/sshkey.py
iotiumlib/user.py
iotiumlib/utils.py
iotiumlib/models/__init__.py
iotiumlib/models/service_listener_creation_vo.py
iotiumlib/models/service_listener_update_vo.py
iotiumlib/models/service_ports_vo.py
iotiumlib/models/service_selector_vo.py
iotiumlib/modules/__init__.py
iotiumlib/modules/cloud/__init__.py
iotiumlib/modules/cloud/ec2.py
iotiumlib/requires/Exceptions.py
iotiumlib/requires/__init__.py
iotiumlib/requires/api_endpoints.py
iotiumlib/requires/commonVariables.py
iotiumlib/requires/commonWrapper.py
iotiumlib/requires/constants.py
iotiumlib/requires/resourcePayload.py
iotiumlib/requires/utils.py
iotiumlib-24.3.21.dist-info/LICENSE
iotiumlib-24.3.21.dist-info/METADATA
iotiumlib-24.3.21.dist-info/WHEEL
iotiumlib-24.3.21.dist-info/top_level.txt
iotiumlib-24.3.21.dist-info/RECORD
