Metadata-Version: 2.1
Name: iotiumlib
Version: 24.3.21
Summary: ioTium API library
Home-page: https://view.com
Author: Rashtrapathy C
Author-email: rashtrapathy.chandrasekar@view.com
License: Copyright 2023 View, Inc. | All Rights Reserved.
Classifier: Programming Language :: Python :: 3.5
Classifier: Operating System :: OS Independent
License-File: LICENSE
Requires-Dist: requests
Requires-Dist: urllib3
Requires-Dist: apache-libcloud
Requires-Dist: boto3
